nightpro/__init__.py
nightpro/main.py
nightpro_for_gopro-1.0.1.dist-info/LICENCE
nightpro_for_gopro-1.0.1.dist-info/METADATA
nightpro_for_gopro-1.0.1.dist-info/WHEEL
nightpro_for_gopro-1.0.1.dist-info/entry_points.txt
nightpro_for_gopro-1.0.1.dist-info/top_level.txt
nightpro_for_gopro-1.0.1.dist-info/RECORD
