Metadata-Version: 2.1
Name: nightpro-for-gopro
Version: 1.0.1
Summary: A nightlapse maker for GoPro
Home-page: https://github.com/pjflanagan/nightpro-for-gopro
Author: Peter James Flanagan
Author-email: pj@pjflanagan.me
License: MIT
Keywords: GoPro nightlapse video
Platform: UNKNOWN
Classifier: Programming Language :: Python :: 3
Classifier: License :: OSI Approved :: MIT License
Classifier: Operating System :: OS Independent
Requires-Python: >=3.6
